ffm3u8/__init__.py
ffm3u8/ffm3u8.py
ffm3u8-1.1.1.dist-info/LICENSE
ffm3u8-1.1.1.dist-info/METADATA
ffm3u8-1.1.1.dist-info/WHEEL
ffm3u8-1.1.1.dist-info/top_level.txt
ffm3u8-1.1.1.dist-info/RECORD
