Metadata-Version: 2.1
Name: ffm3u8
Version: 1.1.1
Summary: A simple TS download module
Home-page: https://github.com/Nong-Yi/ffm3u8.git
Author: Nongyi,企鹅诶i
Author-email: 13360350080@163.com
License: MIT Licence
Requires-Python: >=3.8
License-File: LICENSE
Requires-Dist: requests
Requires-Dist: aiohttp
Requires-Dist: asyncio
Requires-Dist: aiofiles
Requires-Dist: Crypto
